Workbook

Sheet Hit Trax
A1: Code | B1: Title | C1: Artist | D1: Genre
A2: LT2020 | B2: Simon Says | C2: 1910 Fruitgum Company | D2: 1960'S | E2: =LOWER(SUBSTITUTE(B2, " ", "")) -> simonsays
A3: ST6468 | B3: Aria | C3: Acker Bilk | D3: 1960'S | E3: =LOWER(SUBSTITUTE(B3, " ", "")) -> aria
A4: DT1098 | B4: How About That | C4: Adam Faith | D4: 1960'S | E4: =LOWER(SUBSTITUTE(B4, " ", "")) -> howaboutthat
A5: NOY0051 | B5: Take Good Care Of Her | C5: Adam Wade | D5: 1960'S | E5: =LOWER(SUBSTITUTE(B5, " ", "")) -> takegoodcareofher
A6: DT1141 | B6: Mary In The Morning | C6: Al Martino | D6: 1960'S | E6: =LOWER(SUBSTITUTE(B6, " ", "")) -> maryinthemorning
A7: DT1142 | B7: More Than The Eyes Can See | C7: Al Martino | D7: 1960'S | E7: =LOWER(SUBSTITUTE(B7, " ", "")) -> morethantheeyescansee
A8: DT1143 | B8: My Foolish Heart | C8: Al Martino | D8: 1960'S | E8: =LOWER(SUBSTITUTE(B8, " ", "")) -> myfoolishheart
A9: AP2670LB | B9: Spanish Eyes | C9: Al Martino | D9: 1960'S | E9: =LOWER(SUBSTITUTE(B9, " ", "")) -> spanisheyes
A10: DT1144 | B10: Spanish Eyes | C10: Al Martino | D10: 1960'S | E10: =LOWER(SUBSTITUTE(B10, " ", "")) -> spanisheyes
A11: DT1146 | B11: The Snake | C11: Al Wilson | D11: 1960'S | E11: =LOWER(SUBSTITUTE(B11, " ", "")) -> thesnake
A12: DT1148 | B12: Simon Smith And His Amazing … | C12: Alan Price | D12: 1960'S | E12: =LOWER(SUBSTITUTE(B12, " ", "")) -> simonsmithandhisamazing…
A13: ST5976 | B13: The Jarrow Song | C13: Alan Price | D13: 1960'S | E13: =LOWER(SUBSTITUTE(B13, " ", "")) -> thejarrowsong
... A15: DT1150 | B15: Hello Muddah Hello Faddah (A Letter From Camp) | C15: Alan Sherman | D15: 1960'S | E15: =LOWER(SUBSTITUTE(B15, " ", "")) -> hellomuddahhellofaddah(aletterfromcamp)
A16: 101694 | B16: Tighter Tighter | C16: Alive N Kicking | D16: 1960'S | E16: =LOWER(SUBSTITUTE(B16, " ", "")) -> tightertighter
A17: CT1453 | B17: Bell Bottom Blues | C17: Alma Cogan | D17: 1960'S | E17: =LOWER(SUBSTITUTE(B17, " ", "")) -> bellbottomblues
A18: DT7019 | B18: Bend Me Shape Me | C18: Amen Corner | D18: 1960'S | E18: =LOWER(SUBSTITUTE(B18, " ", "")) -> bendmeshapeme
A19: DT7020 | B19: If Paradise Is Half As Nice | C19: Amen Corner | D19: 1960'S | E19: =LOWER(SUBSTITUTE(B19, " ", "")) -> ifparadiseishalfasnice
A20: AP4155DS | B20: Bend Me Shape Me | C20: American Breed | D20: 1960'S | E20: =LOWER(SUBSTITUTE(B20, " ", "")) -> bendmeshapeme
A21: DT1230 | B21: Knock On Wood | C21: Ami Stewart | D21: 1960'S | E21: =LOWER(SUBSTITUTE(B21, " ", "")) -> knockonwood
A22: DT7460 | B22: Let's Live For Today (feat. Vince Gill) | C22: Amy Grant | D22: 1960'S | E22: =LOWER(SUBSTITUTE(B22, " ", "")) -> let'slivefortoday(feat.vincegill)
A23: ST5026 | B23: Almost There | C23: Andy Williams | D23: 1960'S | E23: =LOWER(SUBSTITUTE(B23, " ", "")) -> almostthere
A24: DT1254 | B24: Almost There | C24: Andy Williams | D24: 1960'S | E24: =LOWER(SUBSTITUTE(B24, " ", "")) -> almostthere
A25: DT1255 | B25: Born Free | C25: Andy Williams | D25: 1960'S | E25: =LOWER(SUBSTITUTE(B25, " ", "")) -> bornfree
A26: DT1258 | B26: Days Of Wine And Roses | C26: Andy Williams | D26: 1960'S | E26: =LOWER(SUBSTITUTE(B26, " ", "")) -> daysofwineandroses
A27: DT1260 | B27: Moon River | C27: Andy Williams | D27: 1960'S | E27: =LOWER(SUBSTITUTE(B27, " ", "")) -> moonriver
A28: DT1261 | B28: More And More | C28: Andy Williams | D28: 1960'S | E28: =LOWER(SUBSTITUTE(B28, " ", "")) -> moreandmore
... A39: DT1298 | B39: Who Can I Turn To | C39: Anthony Newley | D39: 1960'S | E39: =LOWER(SUBSTITUTE(B39, " ", "")) -> whocaniturnto
A40: 102184 | B40: Why | C40: Anthony Newley | D40: 1960'S | E40: =LOWER(SUBSTITUTE(B40, " ", "")) -> why
A41: 101647 | B41: Tighten Up | C41: Archie Bell & The Drells | D41: 1960'S | E41: =LOWER(SUBSTITUTE(B41, " ", "")) -> tightenup
A42: DT1313 | B42: Tighten Up | C42: Archie Bell And The Drells | D42: 1960'S | E42: =LOWER(SUBSTITUTE(B42, " ", "")) -> tightenup
A43: NOY0788 | B43: Coming Into Los Angeles | C43: Arlo Guthrie | D43: 1960'S | E43: =LOWER(SUBSTITUTE(B43, " ", "")) -> comingintolosangeles
A44: DT1331 | B44: I Only Have Eyes For You | C44: Art Garfunkel | D44: 1960'S | E44: =LOWER(SUBSTITUTE(B44, " ", "")) -> ionlyhaveeyesforyou
A45: LR1818 | B45: Sweet Soul Music | C45: Arthur Conley | D45: 1960'S | E45: =LOWER(SUBSTITUTE(B45, " ", "")) -> sweetsoulmusic
A46: HO0127 | B46: Nutrocker | C46: B Bumble & Stingers | D46: 1960'S | E46: =LOWER(SUBSTITUTE(B46, " ", "")) -> nutrocker
A47: AP1295H | B47: Raindrops Keep Falling On My Head | C47: B J Thomas | D47: 1960'S | E47: =LOWER(SUBSTITUTE(B47, " ", "")) -> raindropskeepfallingonmyhead
A48: DT1416 | B48: Come And Get It | C48: Badfinger | D48: 1960'S | E48: =LOWER(SUBSTITUTE(B48, " ", "")) -> comeandgetit
A49: DT1429 | B49: Yes I'm Ready | C49: Barbara Mason | D49: 1960'S | E49: =LOWER(SUBSTITUTE(B49, " ", "")) -> yesi'mready
A50: DT1437 | B50: My Man | C50: Barbra Streisand | D50: 1960'S | E50: =LOWER(SUBSTITUTE(B50, " ", "")) -> myman
A51: DT1439 | B51: People | C51: Barbra Streisand | D51: 1960'S | E51: =LOWER(SUBSTITUTE(B51, " ", "")) -> people
A52: DT1440 | B52: Sam, You Made The Pants Too Long | C52: Barbra Streisand | D52: 1960'S | E52: =LOWER(SUBSTITUTE(B52, " ", "")) -> sam,youmadethepantstoolong
A53: DT1441 | B53: Second Hand Rose | C53: Barbra Streisand | D53: 1960'S | E53: =LOWER(SUBSTITUTE(B53, " ", "")) -> secondhandrose
... A57: ST6080 | B57: Don't Forget To Remember | C57: Bee Gees | D57: 1960'S | E57: =LOWER(SUBSTITUTE(B57, " ", "")) -> don'tforgettoremember
A58: 102201 | B58: I Started A Joke | C58: Bee Gees | D58: 1960'S | E58: =LOWER(SUBSTITUTE(B58, " ", "")) -> istartedajoke
A59: 102208 | B59: I've Gotta Get A Message To You | C59: Bee Gees | D59: 1960'S | E59: =LOWER(SUBSTITUTE(B59, " ", "")) -> i'vegottagetamessagetoyou
A60: AP1198H | B60: Massachusetts | C60: Bee Gees | D60: 1960'S | E60: =LOWER(SUBSTITUTE(B60, " ", "")) -> massachusetts
A61: LR0688 | B61: Stand By Me | C61: Ben E King | D61: 1960'S | E61: =LOWER(SUBSTITUTE(B61, " ", "")) -> standbyme
A62: DT1495 | B62: Hole In The Ground | C62: Bernard Cribbins | D62: 1960'S | E62: =LOWER(SUBSTITUTE(B62, " ", "")) -> holeintheground
A63: DT1496 | B63: Right Said Fred | C63: Bernard Cribbins | D63: 1960'S | E63: =LOWER(SUBSTITUTE(B63, " ", "")) -> rightsaidfred
A64: 101459 | B64: The Shoop Shoop Song | C64: Betty Everett | D64: 1960'S | E64: =LOWER(SUBSTITUTE(B64, " ", "")) -> theshoopshoopsong
A65: HT5283 | B65: What Am I Doing Here With You | C65: Bev Harrell | D65: 1960'S | E65: =LOWER(SUBSTITUTE(B65, " ", "")) -> whatamidoingherewithyou
A66: DS1387 | B66: Cuff It (Explicit Version) | C66: Beyonce | D66: 1960'S | E66: =LOWER(SUBSTITUTE(B66, " ", "")) -> cuffit(explicitversion)
A67: DT1515 | B67: Swinging On A Star | C67: Big Dee Irwin | D67: 1960'S | E67: =LOWER(SUBSTITUTE(B67, " ", "")) -> swingingonastar
A68: DT1545 | B68: A Thousand Stars | C68: Billy Fury | D68: 1960'S | E68: =LOWER(SUBSTITUTE(B68, " ", "")) -> athousandstars
A69: CT0075 | B69: Forget Him | C69: Billy Fury | D69: 1960'S | E69: =LOWER(SUBSTITUTE(B69, " ", "")) -> forgethim
A70: LR1310 | B70: Halfway To Paradise | C70: Billy Fury | D70: 1960'S | E70: =LOWER(SUBSTITUTE(B70, " ", "")) -> halfwaytoparadise
A71: ST6097 | B71: I Will | C71: Billy Fury | D71: 1960'S | E71: =LOWER(SUBSTITUTE(B71, " ", "")) -> iwill
A72: DT1546 | B72: In Thoughts Of You | C72: Billy Fury | D72: 1960'S | E72: =LOWER(SUBSTITUTE(B72, " ", "")) -> inthoughtsofyou
A73: CT0074 | B73: Love Or Money | C73: Billy Fury | D73: 1960'S | E73: =LOWER(SUBSTITUTE(B73, " ", "")) -> loveormoney
A74: DT1547 | B74: Maybe Tomorrow | C74: Billy Fury | D74: 1960'S | E74: =LOWER(SUBSTITUTE(B74, " ", "")) -> maybetomorrow
A75: DT1548 | B75: One Upon A Dream | C75: Billy Fury | D75: 1960'S | E75: =LOWER(SUBSTITUTE(B75, " ", "")) -> oneuponadream
A76: NOY1055 | B76: Run To My Loving Arms | C76: Billy Fury | D76: 1960'S | E76: =LOWER(SUBSTITUTE(B76, " ", "")) -> runtomylovingarms
... A119: DT1755 | B119: Ode To Billy Joe | C119: Bobbie Gentry | D119: 1960'S | E119: =LOWER(SUBSTITUTE(B119, " ", "")) -> odetobillyjoe
A120: 101538 | B120: For The Love Of Him | C120: Bobbie Martin | D120: 1960'S | E120: =LOWER(SUBSTITUTE(B120, " ", "")) -> fortheloveofhim
A121: NOY0825 | B121: Walking With My Angel | C121: Bobbie Vee | D121: 1960'S | E121: =LOWER(SUBSTITUTE(B121, " ", "")) -> walkingwithmyangel
A122: HT5558 | B122: I Belong With You | C122: Bobby & Laurie | D122: 1960'S | E122: =LOWER(SUBSTITUTE(B122, " ", "")) -> ibelongwithyou
A123: DT7154 | B123: Montego Bay | C123: Bobby Bloom | D123: 1960'S | E123: =LOWER(SUBSTITUTE(B123, " ", "")) -> montegobay
A124: HDW0133 | B124: Bobby Darin Medley (Swing Low Sweet Chariot/Lonesome Road) | C124: Bobby Darin | D124: 1960'S | E124: =LOWER(SUBSTITUTE(B124, " ", "")) -> bobbydarinmedley(swinglowsweetchariot/lonesomeroad)
A125: DT1745 | B125: Clementine | C125: Bobby Darin | D125: 1960'S | E125: =LOWER(SUBSTITUTE(B125, " ", "")) -> clementine
A126: AP0112 | B126: Dream Lover | C126: Bobby Darin | D126: 1960'S | E126: =LOWER(SUBSTITUTE(B126, " ", "")) -> dreamlover
A127: DT1746 | B127: Lazy River | C127: Bobby Darin | D127: 1960'S | E127: =LOWER(SUBSTITUTE(B127, " ", "")) -> lazyriver
A128: AP0320 | B128: Multiplication | C128: Bobby Darin | D128: 1960'S | E128: =LOWER(SUBSTITUTE(B128, " ", "")) -> multiplication
A129: DT1747 | B129: Multiplication | C129: Bobby Darin | D129: 1960'S | E129: =LOWER(SUBSTITUTE(B129, " ", "")) -> multiplication
A130: AP0099 | B130: Splish Splash | C130: Bobby Darin | D130: 1960'S | E130: =LOWER(SUBSTITUTE(B130, " ", "")) -> splishsplash
A131: DT7158 | B131: Dream Lover | C131: Bobby Darin | D131: 1960'S | E131: =LOWER(SUBSTITUTE(B131, " ", "")) -> dreamlover
A132: DT7159 | B132: La Mer | C132: Bobby Darin | D132: 1960'S | E132: =LOWER(SUBSTITUTE(B132, " ", "")) -> lamer
... A409: NK0037 | B409: Smile | C409: Dean Martin | D409: 1960'S | E409: =LOWER(SUBSTITUTE(B409, " ", "")) -> smile
A410: 101660 | B410: The Glory Of Love | C410: Dean Martin | D410: 1960'S | E410: =LOWER(SUBSTITUTE(B410, " ", "")) -> thegloryoflove
A411: NK0039 | B411: Tik-A-Tee Tik-A-Tay | C411: Dean Martin | D411: 1960'S | E411: =LOWER(SUBSTITUTE(B411, " ", "")) -> tik-a-teetik-a-tay
A412: 102219 | B412: Volare (Nel Blu Di Pinto Di Blu) | C412: Dean Martin | D412: 1960'S | E412: =LOWER(SUBSTITUTE(B412, " ", "")) -> volare(nelbludipintodiblu)
A413: 101672 | B413: Guys N Dolls | C413: Dean Martin & Frank Sinatra | D413: 1960'S | E413: =LOWER(SUBSTITUTE(B413, " ", "")) -> guysndolls
A414: HTX1365 | B414: There's A Ghost In My House | C414: Dean Taylor | D414: 1960'S | E414: =LOWER(SUBSTITUTE(B414, " ", "")) -> there'saghostinmyhouse
A415: HTX0035 | B415: Don't Gild The Lily, Lily | C415: Del Shannon | D415: 1960'S | E415: =LOWER(SUBSTITUTE(B415, " ", "")) -> don'tgildthelily,lily
A416: DT2429 | B416: Hats Off To Larry | C416: Del Shannon | D416: 1960'S | E416: =LOWER(SUBSTITUTE(B416, " ", "")) -> hatsofftolarry
A417: DT2430 | B417: Hey Little Girl | C417: Del Shannon | D417: 1960'S | E417: =LOWER(SUBSTITUTE(B417, " ", "")) -> heylittlegirl
A418: DT2431 | B418: Keep Searching | C418: Del Shannon | D418: 1960'S | E418: =LOWER(SUBSTITUTE(B418, " ", "")) -> keepsearching
A419: NOY1424 | B419: Keep Searching (We'll Follow The Sun) | C419: Del Shannon | D419: 1960'S | E419: =LOWER(SUBSTITUTE(B419, " ", "")) -> keepsearching(we'llfollowthesun)
A420: DT2432 | B420: Little Town Flirt | C420: Del Shannon | D420: 1960'S | E420: =LOWER(SUBSTITUTE(B420, " ", "")) -> littletownflirt
A421: DT2433 | B421: Runaway | C421: Del Shannon | D421: 1960'S | E421: =LOWER(SUBSTITUTE(B421, " ", "")) -> runaway
A422: DT2434 | B422: Swiss Maid | C422: Del Shannon | D422: 1960'S | E422: =LOWER(SUBSTITUTE(B422, " ", "")) -> swissmaid
A423: ST6339 | B423: The Answer To Everything | C423: Del Shannon | D423: 1960'S | E423: =LOWER(SUBSTITUTE(B423, " ", "")) -> theanswertoeverything
A424: DT2435 | B424: Two Kinds Of Teardrops | C424: Del Shannon | D424: 1960'S | E424: =LOWER(SUBSTITUTE(B424, " ", "")) -> twokindsofteardrops
A425: ST6072 | B425: Careless Hands | C425: Des O'connor | D425: 1960'S | E425: =LOWER(SUBSTITUTE(B425, " ", "")) -> carelesshands
... A465: DT2663 | B465: Boys Cry | C465: Eden Kane | D465: 1960'S | E465: =LOWER(SUBSTITUTE(B465, " ", "")) -> boyscry
A466: 101620 | B466: Forget Me Not | C466: Eden Kane | D466: 1960'S | E466: =LOWER(SUBSTITUTE(B466, " ", "")) -> forgetmenot
A467: DT2664 | B467: Forget Me Not | C467: Eden Kane | D467: 1960'S | E467: =LOWER(SUBSTITUTE(B467, " ", "")) -> forgetmenot
A468: AP0964H | B468: Frankenstein | C468: Edgar Winter Group | D468: 1960'S | E468: =LOWER(SUBSTITUTE(B468, " ", "")) -> frankenstein
A469: NOY1604 | B469: Non, Je Ne Regrette Rien | C469: Edith Piaf | D469: 1960'S | E469: =LOWER(SUBSTITUTE(B469, " ", "")) -> non,jeneregretterien
A470: AP1256H | B470: Oh Happy Day | C470: Edwin Hawkins Singers | D470: 1960'S | E470: =LOWER(SUBSTITUTE(B470, " ", "")) -> ohhappyday
A471: ST6284 | B471: S.O.S. (Stop Her On Sight) | C471: Edwin Starr | D471: 1960'S | E471: =LOWER(SUBSTITUTE(B471, " ", "")) -> s.o.s.(stopheronsight)
...

Sheet Music DB in Paper
A1: Database of weather-related popular music songs for paper submitted to Weather : Brown et al. 'Is there a Rhythm Of The Rain? An analysis of weather in popular music'
A2: Based on karafun.com, songfacts.com, bobdylan.com, www.beatlesagain.com and other sources
A3: Primary (P), Secondary (S), Not in database (ND) | B3: Song name | C3: Songwriter | D3: Performers noted in online database (www.karafun.com) | E3: Blizzard | F3: Cloud | G3: Cold / freezing / cool | H3: Fair / blue skies | I3: Fog | J3: Frost | K3: Haze | L3: Heat | M3: Hurricane | N3: Ice | O3: Mist | P3: Rain | Q3: Rainbow | R3: Seasons | S3: Snow | T3: Storm | U3: Sun | V3: Thunder / lightning | W3: Tornado | X3: Wind / breeze | Y3: Clean song name | Z3: Available on Hit Trax (Auto) | AA3: Available on Hit Trax (Manual)
A4: P | B4: 10,000 Nights Of Thunder | C4: Anders Boenloekke | D4: Alphabeat | T4: 1 | V4: 1 | Y4: =LOWER(SUBSTITUTE(CLEAN(B4), " ", "")) -> 10,000nightsofthunder | Z4: =IF(COUNTIF('Hit Trax'!E2:E23901, Y4)>0, 1, 0) -> 0 | AA4: 1
A5: P | B5: A Foggy Day (In London Town) | C5: Ira Gershwin | D5: Michael Bublé | I5: 1 | U5: 1 | Y5: =LOWER(SUBSTITUTE(CLEAN(B5), " ", "")) -> afoggyday(inlondontown) | Z5: =IF(COUNTIF('Hit Trax'!E3:E23902, Y5)>0, 1, 0) -> 0 | AA5: 1
A6: P | B6: A Marshmallow World | C6: Carl Sigman, Peter De Rose | D6: Dean Martin | F6: 1 | G6: 1 | R6: 1 | S6: 1 | U6: 1 | Y6: =LOWER(SUBSTITUTE(CLEAN(B6), " ", "")) -> amarshmallowworld | Z6: =IF(COUNTIF('Hit Trax'!E4:E23903, Y6)>0, 1, 0) -> 0 | AA6: 0
A7: P | B7: A Year Without Rain | C7: Lindy Robbins, Toby Gad | D7: Selena Gomez | P7: 1 | Y7: =LOWER(SUBSTITUTE(CLEAN(B7), " ", "")) -> ayearwithoutrain | Z7: =IF(COUNTIF('Hit Trax'!E5:E23904, Y7)>0, 1, 0) -> 0 | AA7: 0
A8: P | B8: Against The Wind | C8: Bob Seger | D8: Bob Seger | X8: 1 | Y8: =LOWER(SUBSTITUTE(CLEAN(B8), " ", "")) -> againstthewind | Z8: =IF(COUNTIF('Hit Trax'!E6:E23905, Y8)>0, 1, 0) -> 1 | AA8: 1
A9: P | B9: Ain't No Sunshine | C9: Bill Withers | D9: Bill Withers, Eva Cassidy, Michael Bolton, Kris Allen | U9: 1 | Y9: =LOWER(SUBSTITUTE(CLEAN(B9), " ", "")) -> ain'tnosunshine | Z9: =IF(COUNTIF('Hit Trax'!E7:E23906, Y9)>0, 1, 0) -> 1 | AA9: 1
A10: P | B10: April Showers | C10: Jeffrey H. Cohen, Kristian Bush, Jennifer Nettles | D10: SugarLand | P10: 1 | U10: 1 | Y10: =LOWER(SUBSTITUTE(CLEAN(B10), " ", "")) -> aprilshowers | Z10: =IF(COUNTIF('Hit Trax'!E8:E23907, Y10)>0, 1, 0) -> 1 | AA10: 1
A11: P | B11: April Sun In Cuba | C11: Marc Alexander Hunter, Paul Richard Hewson | D11: Dragon | G11: 1 | P11: 1 | R11: 1 | U11: 1 | Y11: =LOWER(SUBSTITUTE(CLEAN(B11), " ", "")) -> aprilsunincuba | Z11: =IF(COUNTIF('Hit Trax'!E9:E23908, Y11)>0, 1, 0) -> 1 | AA11: 1
A12: P | B12: Autumn | C12: Paolo Giovanni Nutini, Jim Duguid | D12: Paolo Nutini | G12: 1 | R12: 1 | Y12: =LOWER(SUBSTITUTE(CLEAN(B12), " ", "")) -> autumn | Z12: =IF(COUNTIF('Hit Trax'!E10:E23909, Y12)>0, 1, 0) -> 0 | AA12: 0
A13: P | B13: Autumn Leaves | C13: Jacques Prévert | D13: Eva Cassidy, Eric Clapton, Paula Cole, Nat King Cole, 1960s Standards | R13: 1 | Y13: =LOWER(SUBSTITUTE(CLEAN(B13), " ", "")) -> autumnleaves | Z13: =IF(COUNTIF('Hit Trax'!E11:E23910, Y13)>0, 1, 0) -> 1 | AA13: 1
A14: P | B14: Baby It's Cold Outside | C14: Frank Loesser | D14: Glee, Dean Martin, Lady Antebellum, Tom Jones | E14: 1 | G14: 1 | L14: 1 | N14: 1 | S14: 1 | T14: 1 | Y14: =LOWER(SUBSTITUTE(CLEAN(B14), " ", "")) -> babyit'scoldoutside | Z14: =IF(COUNTIF('Hit Trax'!E12:E23911, Y14)>0, 1, 0) -> 1 | AA14: 1
A15: P | B15: Before The Storm | C15: Nick Jonas, Kevin Jonas, Joseph Jonas, Miley Cyrus | D15: Jonas Brothers | P15: 1 | T15: 1 | V15: 1 | Y15: =LOWER(SUBSTITUTE(CLEAN(B15), " ", "")) -> beforethestorm | Z15: =IF(COUNTIF('Hit Trax'!E13:E23912, Y15)>0, 1, 0) -> 0 | AA15: 0
A16: P | B16: Black Hole Sun | C16: Chris Cornell | D16: Soundgarden, Paul Anka | G16: 1 | L16: 1 | P16: 1 | R16: 1 | U16: 1 | Y16: =LOWER(SUBSTITUTE(CLEAN(B16), " ", "")) -> blackholesun | Z16: =IF(COUNTIF('Hit Trax'!E14:E23913, Y16)>0, 1, 0) -> 0 | AA16: 0
A17: P | B17: Blowin' In The Wind | C17: Bob Dylan | D17: Bob Dylan, Peter, Paul and Mary | X17: 1 | Y17: =LOWER(SUBSTITUTE(CLEAN(B17), " ", "")) -> blowin'inthewind | Z17: =IF(COUNTIF('Hit Trax'!E15:E23914, Y17)>0, 1, 0) -> 0 | AA17: 0
A18: P | B18: Blowing Kisses In The Wind | C18: Peter Lord Moreland | D18: Paula Abdul | X18: 1 | Y18: =LOWER(SUBSTITUTE(CLEAN(B18), " ", "")) -> blowingkissesinthewind | Z18: =IF(COUNTIF('Hit Trax'!E16:E23915, Y18)>0, 1, 0) -> 0 | AA18: 0
A19: P | B19: Blue Skies (Berlin) | C19: Irving Berlin | D19: Willie Nelson, Eva Cassidy, Rod Stewart | H19: 1 | U19: 1 | Y19: =LOWER(SUBSTITUTE(CLEAN(B19), " ", "")) -> blueskies(berlin) | Z19: =IF(COUNTIF('Hit Trax'!E17:E23916, Y19)>0, 1, 0) -> 0 | AA19: 1
A20: P | B20: Blue Skies (Johnson and Kay) | C20: Matt Johnson, Jay Kay | D20: Jamiroquai | H20: 1 | Y20: =LOWER(SUBSTITUTE(CLEAN(B20), " ", "")) -> blueskies(johnsonandkay) | Z20: =IF(COUNTIF('Hit Trax'!E18:E23917, Y20)>0, 1, 0) -> 0 | AA20: 0
A21: P | B21: Blue Sky | C21: Dickey Betts | D21: The Allman Brothers Band | H21: 1 | U21: 1 | Y21: =LOWER(SUBSTITUTE(CLEAN(B21), " ", "")) -> bluesky | Z21: =IF(COUNTIF('Hit Trax'!E19:E23918, Y21)>0, 1, 0) -> 0 | AA21: 0
A22: P | B22: Brighter Than Sunshine | C22: Matt Hales, Ben Hales, Kimberly Oliver | D22: Aqualung | P22: 1 | U22: 1 | Y22: =LOWER(SUBSTITUTE(CLEAN(B22), " ", "")) -> brighterthansunshine | Z22: =IF(COUNTIF('Hit Trax'!E20:E23919, Y22)>0, 1, 0) -> 0 | AA22: 0
A23: P | B23: Brighter Than The Sun | C23: Ryan Tedder, Colbie Marie Caillat | D23: Colbie Caillat, Smash | U23: 1 | Y23: =LOWER(SUBSTITUTE(CLEAN(B23), " ", "")) -> brighterthanthesun | Z23: =IF(COUNTIF('Hit Trax'!E21:E23920, Y23)>0, 1, 0) -> 1 | AA23: 1
A24: P | B24: Bring Me Sunshine | C24: Sylvia Dee | D24: Morecambe and Wise, The Jive Aces | L24: 1 | U24: 1 | Y24: =LOWER(SUBSTITUTE(CLEAN(B24), " ", "")) -> bringmesunshine | Z24: =IF(COUNTIF('Hit Trax'!E22:E23921, Y24)>0, 1, 0) -> 1 | AA24: 1
A25: P | B25: Bus Stop | C25: Graham Keith Gouldman | D25: The Hollies | P25: 1 | R25: 1 | U25: 1 | X25: 1 | Y25: =LOWER(SUBSTITUTE(CLEAN(B25), " ", "")) -> busstop | Z25: =IF(COUNTIF('Hit Trax'!E23:E23922, Y25)>0, 1, 0) -> 1 | AA25: 1
A26: P | B26: Call Me The Breeze | C26: J. J. Cale | D26: Lynyrd Skynyrd | X26: 1 | Y26: =LOWER(SUBSTITUTE(CLEAN(B26), " ", "")) -> callmethebreeze | Z26: =IF(COUNTIF('Hit Trax'!E24:E23923, Y26)>0, 1, 0) -> 0 | AA26: 0
A27: P | B27: Change The World | C27: Gordon Kennedy, Wayne Kirkpatrick, Tommy Sims | D27: Eric Clapton | U27: 1 | Y27: =LOWER(SUBSTITUTE(CLEAN(B27), " ", "")) -> changetheworld | Z27: =IF(COUNTIF('Hit Trax'!E25:E23924, Y27)>0, 1, 0) -> 1 | AA27: 1
A28: P | B28: Cold As Ice | C28: Kay Denar, Rob Tyger | D28: Sarah Connor | G28: 1 | N28: 1 | S28: 1 | Y28: =LOWER(SUBSTITUTE(CLEAN(B28), " ", "")) -> coldasice | Z28: =IF(COUNTIF('Hit Trax'!E26:E23925, Y28)>0, 1, 0) -> 1 | AA28: 1
A29: P | B29: Cold Day In Hell | C29: Gary Moore | D29: Gary Moore | G29: 1 | Y29: =LOWER(SUBSTITUTE(CLEAN(B29), " ", "")) -> colddayinhell | Z29: =IF(COUNTIF('Hit Trax'!E27:E23926, Y29)>0, 1, 0) -> 0 | AA29: 0
A30: P | B30: Colder Weather | C30: Zac Brown, Wyatt Durette, Levi Lowrey, Coy Bowles | D30: Zac Brown Band | G30: 1 | R30: 1 | U30: 1 | Y30: =LOWER(SUBSTITUTE(CLEAN(B30), " ", "")) -> colderweather | Z30: =IF(COUNTIF('Hit Trax'!E28:E23927, Y30)>0, 1, 0) -> 0 | AA30: 0
A31: P | B31: Come Rain Or Come Shine | C31: Johnny Mercer | D31: Billie Holiday, Frank Sinatra | F31: 1 | P31: 1 | U31: 1 | Y31: =LOWER(SUBSTITUTE(CLEAN(B31), " ", "")) -> comerainorcomeshine | Z31: =IF(COUNTIF('Hit Trax'!E29:E23928, Y31)>0, 1, 0) -> 1 | AA31: 1
A32: P | B32: Cry Cry (Till The Sun Shines) | C32: Marv Green, Aimee Mayo, Chris Lindsey, Hillary Lee Lindsey | D32: Heidi Newfield | F32: 1 | P32: 1 | U32: 1 | Y32: =LOWER(SUBSTITUTE(CLEAN(B32), " ", "")) -> crycry(tillthesunshines) | Z32: =IF(COUNTIF('Hit Trax'!E30:E23929, Y32)>0, 1, 0) -> 0 | AA32: 0
A33: P | B33: Daddy Cool | C33: Frank Farian, George Reyam | D33: Boney M | G33: 1 | Y33: =LOWER(SUBSTITUTE(CLEAN(B33), " ", "")) -> daddycool | Z33: =IF(COUNTIF('Hit Trax'!E31:E23930, Y33)>0, 1, 0) -> 1 | AA33: 1
A34: P | B34: Don't Let The Sun Go Down On Me (Duet/Duet 45 Edit) | C34: Elton John, Bernie Taupin | D34: Elton John, Elton John, Elton John | U34: 1 | Y34: =LOWER(SUBSTITUTE(CLEAN(B34), " ", "")) -> don'tletthesungodownonme(duet/duet45edit) | Z34: =IF(COUNTIF('Hit Trax'!E32:E23931, Y34)>0, 1, 0) -> 0 | AA34: 0
A35: P | B35: Don't Rain On My Parade | C35: Bob Merrill, Jule Styne | D35: Glee, Barbra Streisand | F35: 1 | P35: 1 | U35: 1 | Y35: =LOWER(SUBSTITUTE(CLEAN(B35), " ", "")) -> don'trainonmyparade | Z35: =IF(COUNTIF('Hit Trax'!E33:E23932, Y35)>0, 1, 0) -> 1 | AA35: 1
A36: P | B36: Dust In The Wind | C36: Kerry Livgren | D36: Kansas, Scorpions | X36: 1 | Y36: =LOWER(SUBSTITUTE(CLEAN(B36), " ", "")) -> dustinthewind | Z36: =IF(COUNTIF('Hit Trax'!E34:E23933, Y36)>0, 1, 0) -> 1 | AA36: 1
A37: P | B37: Endless Summer | C37: Blair Mackichan, Andreas Litterscheidt, Marc F Jackson, Reinhard Raith, Hugo Oscar, Oceana Mahlmann, Mense Reents, Jakobus Siebels | D37: Oceana | R37: 1 | Y37: =LOWER(SUBSTITUTE(CLEAN(B37), " ", "")) -> endlesssummer | Z37: =IF(COUNTIF('Hit Trax'!E35:E23934, Y37)>0, 1, 0) -> 0 | AA37: 0
A38: P | B38: Every River | C38: Tom Littlefield, Kim Richey, Angelo Petraglia | D38: Brooks & Dunn | P38: 1 | Y38: =LOWER(SUBSTITUTE(CLEAN(B38), " ", "")) -> everyriver | Z38: =IF(COUNTIF('Hit Trax'!E36:E23935, Y38)>0, 1, 0) -> 0 | AA38: 0
A39: P | B39: Feeling Good | C39: Anthony George Newley, Leslie Bricusse | D39: Michael Bublé, Nina Simone, Muse, Michael Bublé, Adam Lambert, Michael Bublé, Ernestine Anderson | U39: 1 | X39: 1 | Y39: =LOWER(SUBSTITUTE(CLEAN(B39), " ", "")) -> feelinggood | Z39: =IF(COUNTIF('Hit Trax'!E37:E23936, Y39)>0, 1, 0) -> 1 | AA39: 1
A40: P | B40: Fire And Rain | C40: James Warren Taylor | D40: James Warren Taylor | G40: 1 | P40: 1 | U40: 1 | X40: 1 | Y40: =LOWER(SUBSTITUTE(CLEAN(B40), " ", "")) -> fireandrain | Z40: =IF(COUNTIF('Hit Trax'!E38:E23937, Y40)>0, 1, 0) -> 1 | AA40: 1
A41: P | B41: Four Strong Winds | C41: Ian Tyson | D41: Neil Young | R41: 1 | S41: 1 | X41: 1 | Y41: =LOWER(SUBSTITUTE(CLEAN(B41), " ", "")) -> fourstrongwinds | Z41: =IF(COUNTIF('Hit Trax'!E39:E23938, Y41)>0, 1, 0) -> 1 | AA41: 1
A42: P | B42: Frosty The Snowman | C42: Steve Nelson, Walter Rollins | D42: Jazz Standards, Michael Bublé, The Ronettes, Jazzy Christmas | S42: 1 | Y42: =LOWER(SUBSTITUTE(CLEAN(B42), " ", "")) -> frostythesnowman | Z42: =IF(COUNTIF('Hit Trax'!E40:E23939, Y42)>0, 1, 0) -> 1 | AA42: 1
A43: P | B43: Frozen | C43: Daniel Bjorn Gibson, Sharon den Adel, Robert Westerholt | D43: Within Temptation | G43: 1 | Y43: =LOWER(SUBSTITUTE(CLEAN(B43), " ", "")) -> frozen | Z43: =IF(COUNTIF('Hit Trax'!E41:E23940, Y43)>0, 1, 0) -> 1 | AA43: 1
A44: P | B44: Get Off Of My Cloud | C44: Keith Richards | D44: The Rolling Stones | F44: 1 | Y44: =LOWER(SUBSTITUTE(CLEAN(B44), " ", "")) -> getoffofmycloud | Z44: =IF(COUNTIF('Hit Trax'!E42:E23941, Y44)>0, 1, 0) -> 1 | AA44: 1
A45: P | B45: Gone Too Soon | C45: Buz Kohan | D45: Michael Jackson | F45: 1 | Q45: 1 | U45: 1 | Y45: =LOWER(SUBSTITUTE(CLEAN(B45), " ", "")) -> gonetoosoon | Z45: =IF(COUNTIF('Hit Trax'!E43:E23942, Y45)>0, 1, 0) -> 0 | AA45: 0
A46: P | B46: Good Day Sunshine | C46: John Lennon, Paul McCartney | D46: The Beatles | U46: 1 | Y46: =LOWER(SUBSTITUTE(CLEAN(B46), " ", "")) -> gooddaysunshine | Z46: =IF(COUNTIF('Hit Trax'!E44:E23943, Y46)>0, 1, 0) -> 1 | AA46: 1
A47: P | B47: Halo / Walking On Sunshine | C47: Evan Kidd Bogart, Beyoncé, Ryan Tedder, Kimberley Rew | D47: Glee | U47: 1 | Y47: =LOWER(SUBSTITUTE(CLEAN(B47), " ", "")) -> halo/walkingonsunshine | Z47: =IF(COUNTIF('Hit Trax'!E45:E23944, Y47)>0, 1, 0) -> 0 | AA47: 1 | AB47: MB1199 (Originally by Glee, made famous by Beyonce)
A48: P | B48: Have You Ever Seen The Rain? | C48: John Fogerty | D48: Creedence Clearwater Revival, Smokie, Rod Stewart, Bonnie Tyler, Karen Souza | P48: 1 | T48: 1 | U48: 1 | Y48: =LOWER(SUBSTITUTE(CLEAN(B48), " ", "")) -> haveyoueverseentherain? | Z48: =IF(COUNTIF('Hit Trax'!E46:E23945, Y48)>0, 1, 0) -> 0 | AA48: 1 | AB48: HT4105
A49: P | B49: Here Comes The Sun | C49: George Harrison | D49: The Beatles | G49: 1 | N49: 1 | R49: 1 | U49: 1 | Y49: =LOWER(SUBSTITUTE(CLEAN(B49), " ", "")) -> herecomesthesun | Z49: =IF(COUNTIF('Hit Trax'!E47:E23946, Y49)>0, 1, 0) -> 1 | AA49: 1
A50: P | B50: Here's That Rainy Day | C50: James Van Heusen, Johnny Burke | D50: 1950s Standards, Andy Williams | G50: 1 | P50: 1 | Y50: =LOWER(SUBSTITUTE(CLEAN(B50), " ", "")) -> here'sthatrainyday | Z50: =IF(COUNTIF('Hit Trax'!E48:E23947, Y50)>0, 1, 0) -> 0 | AA50: 0
A51: P | B51: Hold Back The Rain | C51: Simon John Charles Lebon, John Taylor, Roger Andrew Taylor, Nick Rhodes, Andy Taylor | D51: Duran Duran | F51: 1 | P51: 1 | X51: 1 | Y51: =LOWER(SUBSTITUTE(CLEAN(B51), " ", "")) -> holdbacktherain | Z51: =IF(COUNTIF('Hit Trax'!E49:E23948, Y51)>0, 1, 0) -> 0 | AA51: 0
A52: P | B52: Hot As Ice | C52: T-Pain | D52: Britney Spears | G52: 1 | L52: 1 | N52: 1 | Y52: =LOWER(SUBSTITUTE(CLEAN(B52), " ", "")) -> hotasice | Z52: =IF(COUNTIF('Hit Trax'!E50:E23949, Y52)>0, 1, 0) -> 0 | AA52: 0
A53: P | B53: Hot Child In The City | C53: Nick Gilder, James Robert McCulloch | D53: Nick Gilder | L53: 1 | Y53: =LOWER(SUBSTITUTE(CLEAN(B53), " ", "")) -> hotchildinthecity | Z53: =IF(COUNTIF('Hit Trax'!E51:E23950, Y53)>0, 1, 0) -> 1 | AA53: 1
A54: P | B54: Hot Fun In The Summertime | C54: Sly Stone | D54: Sly And The Family Stone | F54: 1 | R54: 1 | U54: 1 | Y54: =LOWER(SUBSTITUTE(CLEAN(B54), " ", "")) -> hotfuninthesummertime | Z54: =IF(COUNTIF('Hit Trax'!E52:E23951, Y54)>0, 1, 0) -> 0 | AA54: 0
A55: P | B55: Hot Hot Hot | C55: Alphonsus Cassell | D55: Buster Poindexter, Arrow | L55: 1 | Y55: =LOWER(SUBSTITUTE(CLEAN(B55), " ", "")) -> hothothot | Z55: =IF(COUNTIF('Hit Trax'!E53:E23952, Y55)>0, 1, 0) -> 1 | AA55: 1
A56: P | B56: Hot In The City | C56: Billy Idol | D56: Billy Idol | L56: 1 | Y56: =LOWER(SUBSTITUTE(CLEAN(B56), " ", "")) -> hotinthecity | Z56: =IF(COUNTIF('Hit Trax'!E54:E23953, Y56)>0, 1, 0) -> 0 | AA56: 0
A57: P | B57: Hot Right Now | C57: DJ Fresh, Sian Powell | D57: DJ Fresh | L57: 1 | Y57: =LOWER(SUBSTITUTE(CLEAN(B57), " ", "")) -> hotrightnow | Z57: =IF(COUNTIF('Hit Trax'!E55:E23954, Y57)>0, 1, 0) -> 0 | AA57: 0
A58: P | B58: Hot Stuff | C58: Peter Bellotte, Keith Forsey, Harold Faltermeyer | D58: Donna Summer | L58: 1 | Y58: =LOWER(SUBSTITUTE(CLEAN(B58), " ", "")) -> hotstuff | Z58: =IF(COUNTIF('Hit Trax'!E56:E23955, Y58)>0, 1, 0) -> 1 | AA58: 1
A59: P | B59: Hurricane Drunk | C59: EG White, Florence Leontine Mary Welch | D59: Florence + The Machine | M59: 1 | P59: 1 | T59: 1 | Y59: =LOWER(SUBSTITUTE(CLEAN(B59), " ", "")) -> hurricanedrunk | Z59: =IF(COUNTIF('Hit Trax'!E57:E23956, Y59)>0, 1, 0) -> 0 | AA59: 0
A60: P | B60: I Can't Stand The Rain | C60: Ann Peebles, Donald Bryant, Bernard Miller | D60: Seal, Tina Turner, Tina Turner | P60: 1 | Y60: =LOWER(SUBSTITUTE(CLEAN(B60), " ", "")) -> ican'tstandtherain | Z60: =IF(COUNTIF('Hit Trax'!E58:E23957, Y60)>0, 1, 0) -> 1 | AA60: 1
A61: P | B61: I Love A Rainy Night | C61: David Malloy, Eddie Rabbitt, Even Stevens | D61: Eddie Rabbitt | P61: 1 | U61: 1 | V61: 1 | Y61: =LOWER(SUBSTITUTE(CLEAN(B61), " ", "")) -> ilovearainynight | Z61: =IF(COUNTIF('Hit Trax'!E59:E23958, Y61)>0, 1, 0) -> 1 | AA61: 1
A62: P | B62: I Made It Through The Rain | C62: Jack Feldman, Barry Manilow, Drey Shepperd, Bruce Howard Sussman | D62: Barry Manilow | P62: 1 | T62: 1 | U62: 1 | Y62: =LOWER(SUBSTITUTE(CLEAN(B62), " ", "")) -> imadeitthroughtherain | Z62: =IF(COUNTIF('Hit Trax'!E60:E23959, Y62)>0, 1, 0) -> 0 | AA62: 0
A63: P | B63: I Wish It Could Be Christmas Everyday | C63: Roy Wood | D63: Wizzard | F63: 1 | G63: 1 | S63: 1 | T63: 1 | Y63: =LOWER(SUBSTITUTE(CLEAN(B63), " ", "")) -> iwishitcouldbechristmaseveryday | Z63: =IF(COUNTIF('Hit Trax'!E61:E23960, Y63)>0, 1, 0) -> 1 | AA63: 1
A64: P | B64: Ice, Ice Baby | C64: Freddie Mercury, Brian May, Taylor Roger Meddows, John Deacon | D64: Vanilla Ice, Richard Cheese | L64: 1 | N64: 1 | Y64: =LOWER(SUBSTITUTE(CLEAN(B64), " ", "")) -> ice,icebaby | Z64: =IF(COUNTIF('Hit Trax'!E62:E23961, Y64)>0, 1, 0) -> 0 | AA64: 1 | AB64: HO0129
A65: P | B65: I'll Follow The Sun | C65: John Lennon, Paul McCartney | D65: The Beatles | P65: 1 | U65: 1 | Y65: =LOWER(SUBSTITUTE(CLEAN(B65), " ", "")) -> i'llfollowthesun | Z65: =IF(COUNTIF('Hit Trax'!E63:E23962, Y65)>0, 1, 0) -> 1 | AA65: 1
A66: P | B66: Is It Raining At Your House | C66: Vern Gosdin, Hank Cochran, Dean Dillon | D66: Vern Gosdin | F66: 1 | P66: 1 | U66: 1 | Y66: =LOWER(SUBSTITUTE(CLEAN(B66), " ", "")) -> isitrainingatyourhouse | Z66: =IF(COUNTIF('Hit Trax'!E64:E23963, Y66)>0, 1, 0) -> 0 | AA66: 0
A67: P | B67: Island In The Sun | C67: Rivers Cuomo | D67: Weezer | U67: 1 | Y67: =LOWER(SUBSTITUTE(CLEAN(B67), " ", "")) -> islandinthesun | Z67: =IF(COUNTIF('Hit Trax'!E65:E23964, Y67)>0, 1, 0) -> 1 | AA67: 1
A68: P | B68: It Might As Well Rain Until September | C68: Gerald Goffin, Carole King | D68: Carole King | H68: 1 | P68: 1 | R68: 1 | U68: 1 | Y68: =LOWER(SUBSTITUTE(CLEAN(B68), " ", "")) -> itmightaswellrainuntilseptember | Z68: =IF(COUNTIF('Hit Trax'!E66:E23965, Y68)>0, 1, 0) -> 1 | AA68: 1
A69: P | B69: It Never Rains In Southern California (Hazelwood and Hammond) | C69: Mike Hazelwood, Albert Louis Hammond | D69: Smokie | P69: 1 | Y69: =LOWER(SUBSTITUTE(CLEAN(B69), " ", "")) -> itneverrainsinsoutherncalifornia(hazelwoodandhammond) | Z69: =IF(COUNTIF('Hit Trax'!E67:E23966, Y69)>0, 1, 0) -> 0 | AA69: 1 | AB69: NOY1538
A70: P | B70: It's Raining Again | C70: Roger Hodgson, Rick Davies | D70: Supertramp | P70: 1 | U70: 1 | Y70: =LOWER(SUBSTITUTE(CLEAN(B70), " ", "")) -> it'srainingagain | Z70: =IF(COUNTIF('Hit Trax'!E68:E23967, Y70)>0, 1, 0) -> 1 | AA70: 1
A71: P | B71: It's Raining Men | C71: Paul Jabara | D71: Weather Girls, Geri Halliwell | P71: 1 | V71: 1 | Y71: =LOWER(SUBSTITUTE(CLEAN(B71), " ", "")) -> it'srainingmen | Z71: =IF(COUNTIF('Hit Trax'!E69:E23968, Y71)>0, 1, 0) -> 1 | AA71: 1
A72: P | B72: It's Raining On Prom Night | C72: Jim Jacobs, Warren Casey | D72: Cindy Bullens | P72: 1 | T72: 1 | Y72: =LOWER(SUBSTITUTE(CLEAN(B72), " ", "")) -> it'srainingonpromnight | Z72: =IF(COUNTIF('Hit Trax'!E70:E23969, Y72)>0, 1, 0) -> 1 | AA72: 1
A73: P | B73: I've Got The World On A String | C73: Ted Koehler | D73: Frank Sinatra, Michael Bublé, Céline Dion, Michael Bublé | P73: 1 | Q73: 1 | Y73: =LOWER(SUBSTITUTE(CLEAN(B73), " ", "")) -> i'vegottheworldonastring | Z73: =IF(COUNTIF('Hit Trax'!E71:E23970, Y73)>0, 1, 0) -> 1 | AA73: 1
A74: P | B74: Just Walkin' In The Rain | C74: Johnny Bragg, Stantley Robert Riley | D74: Johnnie Ray | P74: 1 | Y74: =LOWER(SUBSTITUTE(CLEAN(B74), " ", "")) -> justwalkin'intherain | Z74: =IF(COUNTIF('Hit Trax'!E72:E23971, Y74)>0, 1, 0) -> 1 | AA74: 1
A75: P | B75: Keep On The Sunny Side | C75: A.P. Carter | D75: The Whites | F75: 1 | H75: 1 | T75: 1 | U75: 1 | Y75: =LOWER(SUBSTITUTE(CLEAN(B75), " ", "")) -> keeponthesunnyside | Z75: =IF(COUNTIF('Hit Trax'!E73:E23972, Y75)>0, 1, 0) -> 0 | AA75: 0
A76: P | B76: Let It Rain (Hall) | C76: Kristen Hall | D76: Amanda Marshall | P76: 1 | Y76: =LOWER(SUBSTITUTE(CLEAN(B76), " ", "")) -> letitrain(hall) | Z76: =IF(COUNTIF('Hit Trax'!E74:E23973, Y76)>0, 1, 0) -> 0 | AA76: 1 | AB76: AP4303MB
A77: P | B77: Let It Rain (Farren) | C77: Michael Farren | D77: Michael W. Smith | F77: 1 | P77: 1 | V77: 1 | Y77: =LOWER(SUBSTITUTE(CLEAN(B77), " ", "")) -> letitrain(farren) | Z77: =IF(COUNTIF('Hit Trax'!E75:E23974, Y77)>0, 1, 0) -> 0 | AA77: 0
A78: P | B78: Let It Snow! Let It Snow! Let It Snow! | C78: Sammy Cahn | D78: Michael Bublé, Lady Antebellum, Dean Martin, 1940s Standards, Vaughn Monroe, Vaughn Monroe | L78: 1 | S78: 1 | T78: 1 | Y78: =LOWER(SUBSTITUTE(CLEAN(B78), " ", "")) -> letitsnow!letitsnow!letitsnow! | Z78: =IF(COUNTIF('Hit Trax'!E76:E23975, Y78)>0, 1, 0) -> 1 | AA78: 1
A79: P | B79: Lightning Crashes | C79: Patrick Michael Dahlheimer, Chad Alan Gracey, Chad Taylor, Ed Kowalczyk | D79: Live | V79: 1 | X79: 1 | Y79: =LOWER(SUBSTITUTE(CLEAN(B79), " ", "")) -> lightningcrashes | Z79: =IF(COUNTIF('Hit Trax'!E77:E23976, Y79)>0, 1, 0) -> 1 | AA79: 1
A80: P | B80: Lion In The Morning Sun | C80: Will Rendle, John Stewart Tilley | D80: Will And The People | U80: 1 | Y80: =LOWER(SUBSTITUTE(CLEAN(B80), " ", "")) -> lioninthemorningsun | Z80: =IF(COUNTIF('Hit Trax'!E78:E23977, Y80)>0, 1, 0) -> 0 | AA80: 0
A81: P | B81: Liza (All The Clouds'll Roll Away) | C81: George Gershwin, Ira Gershwin | D81: Al Johnson | F81: 1 | X81: 1 | Y81: =LOWER(SUBSTITUTE(CLEAN(B81), " ", "")) -> liza(alltheclouds'llrollaway) | Z81: =IF(COUNTIF('Hit Trax'!E79:E23978, Y81)>0, 1, 0) -> 0 | AA81: 0
A82: P | B82: (Love Is Like A) Heat Wave | C82: Eddie Holland, Lamont Herbert Dozier, Brian Holland | D82: Martha and the Vandellas, Phil Collins | L82: 1 | Y82: =LOWER(SUBSTITUTE(CLEAN(B82), " ", "")) -> (loveislikea)heatwave | Z82: =IF(COUNTIF('Hit Trax'!E80:E23979, Y82)>0, 1, 0) -> 0 | AA82: 0
A83: P | B83: MacArthur Park | C83: Jimmy Layne Webb | D83: Richard Harris | L83: 1 | P83: 1 | U83: 1 | Y83: =LOWER(SUBSTITUTE(CLEAN(B83), " ", "")) -> macarthurpark | Z83: =IF(COUNTIF('Hit Trax'!E81:E23980, Y83)>0, 1, 0) -> 1 | AA83: 1
A84: P | B84: Make It Rain | C84: Jody Stevens, James Michael Harrison | D84: Fast Ryde | P84: 1 | Y84: =LOWER(SUBSTITUTE(CLEAN(B84), " ", "")) -> makeitrain | Z84: =IF(COUNTIF('Hit Trax'!E82:E23981, Y84)>0, 1, 0) -> 0 | AA84: 0
A85: P | B85: Mercy Mercy Me (The Ecology) | C85: Marvin Gaye | D85: Marvin Gaye | H85: 1 | X85: 1 | Y85: =LOWER(SUBSTITUTE(CLEAN(B85), " ", "")) -> mercymercyme(theecology) | Z85: =IF(COUNTIF('Hit Trax'!E83:E23982, Y85)>0, 1, 0) -> 0 | AA85: 1 | AB85: AP1201H
A86: P | B86: Miss You Most (At Christmas Time) | C86: Walter Afanasieff, Mariah Carey | D86: Mariah Carey | G86: 1 | R86: 1 | S86: 1 | Y86: =LOWER(SUBSTITUTE(CLEAN(B86), " ", "")) -> missyoumost(atchristmastime) | Z86: =IF(COUNTIF('Hit Trax'!E84:E23983, Y86)>0, 1, 0) -> 0 | AA86: 0
A87: P | B87: Misty Blue | C87: Bob Montgomery | D87: Dorothy Moore | O87: 1 | Y87: =LOWER(SUBSTITUTE(CLEAN(B87), " ", "")) -> mistyblue | Z87: =IF(COUNTIF('Hit Trax'!E85:E23984, Y87)>0, 1, 0) -> 1 | AA87: 1
A88: P | B88: Morning Sun | C88: Robbie Williams, Daniel Spencer Mould, Kevin Andrews, Scott Andrew Ralph, Richard Scott | D88: Robbie Williams | Q88: 1 | U88: 1 | Y88: =LOWER(SUBSTITUTE(CLEAN(B88), " ", "")) -> morningsun | Z88: =IF(COUNTIF('Hit Trax'!E86:E23985, Y88)>0, 1, 0) -> 1 | AA88: 1
A89: P | B89: Mr Dieingly Sad | C89: Don Ciccone | D89: The Critters | P89: 1 | R89: 1 | X89: 1 | Y89: =LOWER(SUBSTITUTE(CLEAN(B89), " ", "")) -> mrdieinglysad | Z89: =IF(COUNTIF('Hit Trax'!E87:E23986, Y89)>0, 1, 0) -> 0 | AA89: 0
A90: P | B90: Mr. Blue Sky | C90: Jeff Lynne | D90: Electric Light Orchestra | F90: 1 | H90: 1 | P90: 1 | U90: 1 | Y90: =LOWER(SUBSTITUTE(CLEAN(B90), " ", "")) -> mr.bluesky | Z90: =IF(COUNTIF('Hit Trax'!E88:E23987, Y90)>0, 1, 0) -> 0 | AA90: 1 | AB90: DT2629
A91: P | B91: North Wind | C91: Rod Morris | D91: Slim Whitman | X91: 1 | Y91: =LOWER(SUBSTITUTE(CLEAN(B91), " ", "")) -> northwind | Z91: =IF(COUNTIF('Hit Trax'!E89:E23988, Y91)>0, 1, 0) -> 0 | AA91: 0
A92: P | B92: Oh What A Beautiful Morning | C92: Oscar Hammerstein II | D92: Oklahoma | K92: 1 | X92: 1 | Y92: =LOWER(SUBSTITUTE(CLEAN(B92), " ", "")) -> ohwhatabeautifulmorning | Z92: =IF(COUNTIF('Hit Trax'!E90:E23989, Y92)>0, 1, 0) -> 1 | AA92: 1
A93: P | B93: On The Sunny Side Of The Street | C93: Dorothy Fields | D93: Frankie Lane, Frank Sinatra | U93: 1 | Y93: =LOWER(SUBSTITUTE(CLEAN(B93), " ", "")) -> onthesunnysideofthestreet | Z93: =IF(COUNTIF('Hit Trax'!E91:E23990, Y93)>0, 1, 0) -> 1 | AA93: 1
A94: P | B94: One Way Wind | C94: Arnoldus D A Muehren | D94: The Cats | X94: 1 | Y94: =LOWER(SUBSTITUTE(CLEAN(B94), " ", "")) -> onewaywind | Z94: =IF(COUNTIF('Hit Trax'!E92:E23991, Y94)>0, 1, 0) -> 0 | AA94: 0
A95: P | B95: Over The Rainbow / What A Wonderful World | C95: Edgar Yipsel Harburg | D95: Israel Kamakawiwo'ole | F95: 1 | H95: 1 | Q95: 1 | Y95: =LOWER(SUBSTITUTE(CLEAN(B95), " ", "")) -> overtherainbow/whatawonderfulworld | Z95: =IF(COUNTIF('Hit Trax'!E93:E23992, Y95)>0, 1, 0) -> 0 | AA95: 1 | AB95: CTS0076 and others (wizard of oz)
A96: P | B96: Please Mr Sun | C96: Sid Frank | D96: Johnnie Ray | P96: 1 | Q96: 1 | U96: 1 | X96: 1 | Y96: =LOWER(SUBSTITUTE(CLEAN(B96), " ", "")) -> pleasemrsun | Z96: =IF(COUNTIF('Hit Trax'!E94:E23993, Y96)>0, 1, 0) -> 0 | AA96: 0
A97: P | B97: Pocketful Of Sunshine | C97: Natasha Anne Bedingfield, Danielle Brisebois, John M Shanks | D97: Natasha Bedingfield | U97: 1 | Y97: =LOWER(SUBSTITUTE(CLEAN(B97), " ", "")) -> pocketfulofsunshine | Z97: =IF(COUNTIF('Hit Trax'!E95:E23994, Y97)>0, 1, 0) -> 0 | AA97: 0
A98: P | B98: Powder Your Face With Sunshine | C98: Carmen Lombardo, Stanley Rochinski | D98: Dean Martin | U98: 1 | Y98: =LOWER(SUBSTITUTE(CLEAN(B98), " ", "")) -> powderyourfacewithsunshine | Z98: =IF(COUNTIF('Hit Trax'!E96:E23995, Y98)>0, 1, 0) -> 0 | AA98: 0
A99: P | B99: Purple Rain | C99: Prince | D99: Etta James, Prince | P99: 1 | Y99: =LOWER(SUBSTITUTE(CLEAN(B99), " ", "")) -> purplerain | Z99: =IF(COUNTIF('Hit Trax'!E97:E23996, Y99)>0, 1, 0) -> 1 | AA99: 1
A100: P | B100: Rain (Lennon and McCartney) | C100: John Lennon, Paul McCartney | D100: The Beatles | P100: 1 | U100: 1 | Y100: =LOWER(SUBSTITUTE(CLEAN(B100), " ", "")) -> rain(lennonandmccartney) | Z100: =IF(COUNTIF('Hit Trax'!E98:E23997, Y100)>0, 1, 0) -> 0 | AA100: 1 | AB100: NOY1526
...
